grasshopper_mcp/__init__.py
grasshopper_mcp/bridge.py
grasshopper_mcp-0.1.0.dist-info/METADATA
grasshopper_mcp-0.1.0.dist-info/WHEEL
grasshopper_mcp-0.1.0.dist-info/entry_points.txt
grasshopper_mcp-0.1.0.dist-info/top_level.txt
grasshopper_mcp-0.1.0.dist-info/RECORD
