Metadata-Version: 2.2
Name: grasshopper-mcp
Version: 0.1.0
Summary: Grasshopper MCP Bridge Server
Home-page: https://github.com/alfredatnycu/grasshopper-mcp
Author: Alfred Chen
Author-email: yanlin.hs12@nycu.edu.tw
Keywords: grasshopper,mcp,bridge,server
Classifier: Development Status :: 3 - Alpha
Classifier: Intended Audience :: Developers
Classifier: Programming Language :: Python :: 3
Classifier: Programming Language :: Python :: 3.8
Classifier: Programming Language :: Python :: 3.9
Requires-Python: >=3.8
Requires-Dist: mcp>=0.1.0
Requires-Dist: websockets>=10.0
Requires-Dist: aiohttp>=3.8.0
Dynamic: author
Dynamic: author-email
Dynamic: classifier
Dynamic: description
Dynamic: description-content-type
Dynamic: home-page
Dynamic: keywords
Dynamic: requires-dist
Dynamic: requires-python
Dynamic: summary
